CHANGELOG.md
LICENSE
MANIFEST.in
README.md
pyproject.toml
release.md
requirements.txt
setup.py
iddefix/__init__.py
iddefix/_version.py
iddefix/framework.py
iddefix/objectiveFunctions.py
iddefix/resonatorFormulas.py
iddefix/smartBoundDetermination.py
iddefix/solvers.py
iddefix/utils.py
iddefix.egg-info/PKG-INFO
iddefix.egg-info/SOURCES.txt
iddefix.egg-info/dependency_links.txt
iddefix.egg-info/requires.txt
iddefix.egg-info/top_level.txt
tests/test_001_fft.py
tests/test_002_deconvolution.py
tests/test_003_analytical_impedance.py