Metadata-Version: 2.2
Name: iddefix
Version: 0.1.3
Summary: Genetic Algorithm Resonator Fitting for Impedance ExtrapoLation and Determination
Home-page: https://github.com/ImpedanCEI/IDDEFIX
Download-URL: https://pypi.python.org/pypi/iddefix
Author: Sebastien Joly
Author-email: sebastien.joly@helmholtz-berlin.de
Maintainer: Elena de la Fuente
Maintainer-email: elena.de.la.fuente.garcia@cern.ch
License: GNU GENERAL PUBLIC LICENSE
Project-URL: Bug Tracker, https://github.com/ImpedanCEI/IDDEFIX/issues
Project-URL: Documentation, https://iddefix.readthedocs.io/en/latest/.html
Project-URL: Source Code, https://github.com/ImpedanCEI/IDDEFIX/
Classifier: Development Status :: 4 - Beta
Classifier: Programming Language :: Python :: 3
Classifier: Operating System :: OS Independent
Classifier: Intended Audience :: Science/Research
Classifier: Topic :: Scientific/Engineering :: Physics
License-File: LICENSE
Requires-Dist: numpy<2.0
Requires-Dist: scipy
Requires-Dist: pymoo
Provides-Extra: all
Requires-Dist: numpy; extra == "all"
Requires-Dist: scipy; extra == "all"
Requires-Dist: pyfde; extra == "all"
Requires-Dist: pymoo; extra == "all"
Dynamic: author
Dynamic: author-email
Dynamic: classifier
Dynamic: description
Dynamic: description-content-type
Dynamic: download-url
Dynamic: home-page
Dynamic: license
Dynamic: maintainer
Dynamic: maintainer-email
Dynamic: project-url
Dynamic: provides-extra
Dynamic: requires-dist
Dynamic: summary
